alacorderdev/__init__.py
alacorderdev/__main__.py
alacorderdev/alac.py
alacorderdev-7.2.4.dist-info/LICENSE
alacorderdev-7.2.4.dist-info/METADATA
alacorderdev-7.2.4.dist-info/WHEEL
alacorderdev-7.2.4.dist-info/top_level.txt
alacorderdev-7.2.4.dist-info/RECORD
