Metadata-Version: 2.1
Name: alacorderdev
Version: 7.2.4
Summary: pure-python
Author-email: Sam Robson <sbrobson@crimson.ua.edu>
Classifier: Programming Language :: Python :: 3
Classifier: License :: OSI Approved :: MIT License
Classifier: Operating System :: OS Independent
Requires-Python: >=3.7
License-File: LICENSE
Requires-Dist: pandas
Requires-Dist: numpy
Requires-Dist: xlrd
Requires-Dist: openpyxl
Requires-Dist: setuptools
Requires-Dist: PyPDF2
Requires-Dist: xlwt
Requires-Dist: build
Requires-Dist: pip
Requires-Dist: jupyter
